Metadata-Version: 2.1
Name: multiformats-fix
Version: 0.2.3
Summary: Python implementation of multiformats protocols.
Author-email: aviksaikat <saikickkarma@protonmail.com>
Project-URL: Homepage, https://github.com/aviksaikat/multiformats
Project-URL: Issues, https://github.com/aviksaikat/multiformats/issues
Classifier: Development Status :: 3 - Alpha
Classifier: Programming Language :: Python :: 3.10
Classifier: Programming Language :: Python :: 3.9
Classifier: Programming Language :: Python :: 3.8
Classifier: Operating System :: OS Independent
Classifier: Natural Language :: English
Classifier: Typing :: Typed
Requires-Python: >=3.8
License-File: LICENSE
Requires-Dist: typing-extensions
Requires-Dist: makkus.bases
Requires-Dist: makkus.multiformats-config
Requires-Dist: typing-validation-fix
Provides-Extra: dev
Requires-Dist: mypy ; extra == 'dev'
Requires-Dist: pylint ; extra == 'dev'
Requires-Dist: pytest ; extra == 'dev'
Requires-Dist: pytest-cov ; extra == 'dev'
Requires-Dist: pysha3 ; extra == 'dev'
Requires-Dist: blake3 ; extra == 'dev'
Requires-Dist: pyskein ; extra == 'dev'
Requires-Dist: mmh3 ; extra == 'dev'
Requires-Dist: pycryptodomex ; extra == 'dev'
Provides-Extra: full
Requires-Dist: pysha3 ; extra == 'full'
Requires-Dist: blake3 ; extra == 'full'
Requires-Dist: pyskein ; extra == 'full'
Requires-Dist: mmh3 ; extra == 'full'
Requires-Dist: pycryptodomex ; extra == 'full'
